scigpt/__init__.py
scigpt/chatgpt.py
scigpt-2023.3.24.dist-info/LICENSE
scigpt-2023.3.24.dist-info/METADATA
scigpt-2023.3.24.dist-info/WHEEL
scigpt-2023.3.24.dist-info/top_level.txt
scigpt-2023.3.24.dist-info/RECORD
