Metadata-Version: 2.1
Name: scigpt
Version: 2023.3.24
Summary: scigpt
Home-page: https://github.com/deepmaterials/scipgpt
Author: Kamal Choudhary
Author-email: writetokamal.1989@gmail.com
License: UNKNOWN
Platform: UNKNOWN
Classifier: Programming Language :: Python :: 3
Classifier: Operating System :: OS Independent
Requires-Python: >=3.7
Requires-Dist: numpy (>=1.22.0)
Requires-Dist: scipy (>=1.6.3)
Requires-Dist: jarvis-tools (>=2021.07.19)
Requires-Dist: openai
Requires-Dist: chemnlp
Requires-Dist: matplotlib (>=3.4.1)
Requires-Dist: flake8 (>=3.9.1)
Requires-Dist: pycodestyle (>=2.7.0)
Requires-Dist: pydocstyle (>=6.0.0)
